<annotation>
	<folder>BacterialBlight</folder>
	<filename>1401.jpg</filename>
	<path>D:\666\YOLOV5\paper_data\VOC2024\images\BacterialBlight\1401.jpg</path>
	<source>
		<database>Unknown</database>
	</source>
	<size>
		<width>300</width>
		<height>300</height>
		<depth>3</depth>
	</size>
	<segmented>0</segmented>
	<object>
		<name>BacterialBlight</name>
		<pose>Unspecified</pose>
		<truncated>0</truncated>
		<difficult>0</difficult>
		<bndbox>
			<xmin>179</xmin>
			<ymin>2</ymin>
			<xmax>188</xmax>
			<ymax>47</ymax>
		</bndbox>
	</object>
	<object>
		<name>BacterialBlight</name>
		<pose>Unspecified</pose>
		<truncated>0</truncated>
		<difficult>0</difficult>
		<bndbox>
			<xmin>176</xmin>
			<ymin>49</ymin>
			<xmax>183</xmax>
			<ymax>84</ymax>
		</bndbox>
	</object>
	<object>
		<name>BacterialBlight</name>
		<pose>Unspecified</pose>
		<truncated>0</truncated>
		<difficult>0</difficult>
		<bndbox>
			<xmin>174</xmin>
			<ymin>86</ymin>
			<xmax>181</xmax>
			<ymax>151</ymax>
		</bndbox>
	</object>
	<object>
		<name>BacterialBlight</name>
		<pose>Unspecified</pose>
		<truncated>0</truncated>
		<difficult>0</difficult>
		<bndbox>
			<xmin>170</xmin>
			<ymin>151</ymin>
			<xmax>175</xmax>
			<ymax>206</ymax>
		</bndbox>
	</object>
	<object>
		<name>BacterialBlight</name>
		<pose>Unspecified</pose>
		<truncated>1</truncated>
		<difficult>0</difficult>
		<bndbox>
			<xmin>167</xmin>
			<ymin>207</ymin>
			<xmax>177</xmax>
			<ymax>300</ymax>
		</bndbox>
	</object>
</annotation>
