<annotation>
	<folder>BrownSpot</folder>
	<filename>1892.jpg</filename>
	<path>D:\666\YOLOV5\paper_data\VOC2024\images\BrownSpot\1892.jpg</path>
	<source>
		<database>Unknown</database>
	</source>
	<size>
		<width>1623</width>
		<height>1623</height>
		<depth>3</depth>
	</size>
	<segmented>0</segmented>
	<object>
		<name>BrownSpot</name>
		<pose>Unspecified</pose>
		<truncated>0</truncated>
		<difficult>0</difficult>
		<bndbox>
			<xmin>720</xmin>
			<ymin>62</ymin>
			<xmax>935</xmax>
			<ymax>323</ymax>
		</bndbox>
	</object>
	<object>
		<name>BrownSpot</name>
		<pose>Unspecified</pose>
		<truncated>1</truncated>
		<difficult>0</difficult>
		<bndbox>
			<xmin>801</xmin>
			<ymin>1435</ymin>
			<xmax>1129</xmax>
			<ymax>1623</ymax>
		</bndbox>
	</object>
</annotation>
