<annotation>
	<folder>BrownSpot</folder>
	<filename>2002.jpg</filename>
	<path>D:\666\YOLOV5\paper_data\VOC2024\images\BrownSpot\2002.jpg</path>
	<source>
		<database>Unknown</database>
	</source>
	<size>
		<width>2263</width>
		<height>2263</height>
		<depth>3</depth>
	</size>
	<segmented>0</segmented>
	<object>
		<name>BrownSpot</name>
		<pose>Unspecified</pose>
		<truncated>0</truncated>
		<difficult>0</difficult>
		<bndbox>
			<xmin>520</xmin>
			<ymin>1196</ymin>
			<xmax>656</xmax>
			<ymax>1321</ymax>
		</bndbox>
	</object>
	<object>
		<name>BrownSpot</name>
		<pose>Unspecified</pose>
		<truncated>0</truncated>
		<difficult>0</difficult>
		<bndbox>
			<xmin>758</xmin>
			<ymin>1456</ymin>
			<xmax>975</xmax>
			<ymax>1646</ymax>
		</bndbox>
	</object>
	<object>
		<name>BrownSpot</name>
		<pose>Unspecified</pose>
		<truncated>0</truncated>
		<difficult>0</difficult>
		<bndbox>
			<xmin>1006</xmin>
			<ymin>1021</ymin>
			<xmax>1159</xmax>
			<ymax>1124</ymax>
		</bndbox>
	</object>
	<object>
		<name>BrownSpot</name>
		<pose>Unspecified</pose>
		<truncated>0</truncated>
		<difficult>0</difficult>
		<bndbox>
			<xmin>1524</xmin>
			<ymin>624</ymin>
			<xmax>1699</xmax>
			<ymax>728</ymax>
		</bndbox>
	</object>
	<object>
		<name>BrownSpot</name>
		<pose>Unspecified</pose>
		<truncated>0</truncated>
		<difficult>0</difficult>
		<bndbox>
			<xmin>2074</xmin>
			<ymin>510</ymin>
			<xmax>2224</xmax>
			<ymax>653</ymax>
		</bndbox>
	</object>
	<object>
		<name>BrownSpot</name>
		<pose>Unspecified</pose>
		<truncated>1</truncated>
		<difficult>0</difficult>
		<bndbox>
			<xmin>2202</xmin>
			<ymin>155</ymin>
			<xmax>2263</xmax>
			<ymax>226</ymax>
		</bndbox>
	</object>
</annotation>
