<annotation>
	<folder>BrownSpot</folder>
	<filename>2067.jpg</filename>
	<path>D:\666\YOLOV5\paper_data\VOC2024\images\BrownSpot\2067.jpg</path>
	<source>
		<database>Unknown</database>
	</source>
	<size>
		<width>2270</width>
		<height>2270</height>
		<depth>3</depth>
	</size>
	<segmented>0</segmented>
	<object>
		<name>BrownSpot</name>
		<pose>Unspecified</pose>
		<truncated>0</truncated>
		<difficult>0</difficult>
		<bndbox>
			<xmin>1224</xmin>
			<ymin>1157</ymin>
			<xmax>1378</xmax>
			<ymax>1241</ymax>
		</bndbox>
	</object>
	<object>
		<name>BrownSpot</name>
		<pose>Unspecified</pose>
		<truncated>0</truncated>
		<difficult>0</difficult>
		<bndbox>
			<xmin>1228</xmin>
			<ymin>1227</ymin>
			<xmax>1346</xmax>
			<ymax>1319</ymax>
		</bndbox>
	</object>
</annotation>
