<annotation>
	<folder>Healthy</folder>
	<filename>2455.jpg</filename>
	<path>D:\666\YOLOV5\paper_data\VOC2024\images\Healthy\2455.jpg</path>
	<source>
		<database>Unknown</database>
	</source>
	<size>
		<width>2312</width>
		<height>2312</height>
		<depth>3</depth>
	</size>
	<segmented>0</segmented>
	<object>
		<name>Healthy</name>
		<pose>Unspecified</pose>
		<truncated>1</truncated>
		<difficult>0</difficult>
		<bndbox>
			<xmin>4</xmin>
			<ymin>616</ymin>
			<xmax>2312</xmax>
			<ymax>1883</ymax>
		</bndbox>
	</object>
</annotation>
