<annotation>
	<folder>Hispa</folder>
	<filename>3999.jpg</filename>
	<path>D:\666\YOLOV5\paper_data\VOC2024\images\Hispa\3999.jpg</path>
	<source>
		<database>Unknown</database>
	</source>
	<size>
		<width>2402</width>
		<height>2402</height>
		<depth>3</depth>
	</size>
	<segmented>0</segmented>
	<object>
		<name>Hispa</name>
		<pose>Unspecified</pose>
		<truncated>0</truncated>
		<difficult>0</difficult>
		<bndbox>
			<xmin>874</xmin>
			<ymin>874</ymin>
			<xmax>932</xmax>
			<ymax>914</ymax>
		</bndbox>
	</object>
	<object>
		<name>Hispa</name>
		<pose>Unspecified</pose>
		<truncated>0</truncated>
		<difficult>0</difficult>
		<bndbox>
			<xmin>905</xmin>
			<ymin>909</ymin>
			<xmax>943</xmax>
			<ymax>934</ymax>
		</bndbox>
	</object>
	<object>
		<name>Hispa</name>
		<pose>Unspecified</pose>
		<truncated>0</truncated>
		<difficult>0</difficult>
		<bndbox>
			<xmin>1753</xmin>
			<ymin>1586</ymin>
			<xmax>1813</xmax>
			<ymax>1636</ymax>
		</bndbox>
	</object>
	<object>
		<name>Hispa</name>
		<pose>Unspecified</pose>
		<truncated>0</truncated>
		<difficult>0</difficult>
		<bndbox>
			<xmin>1868</xmin>
			<ymin>1655</ymin>
			<xmax>1901</xmax>
			<ymax>1688</ymax>
		</bndbox>
	</object>
	<object>
		<name>Hispa</name>
		<pose>Unspecified</pose>
		<truncated>1</truncated>
		<difficult>0</difficult>
		<bndbox>
			<xmin>2303</xmin>
			<ymin>1786</ymin>
			<xmax>2402</xmax>
			<ymax>1870</ymax>
		</bndbox>
	</object>
</annotation>
