<annotation>
	<folder>Hispa</folder>
	<filename>4056.jpg</filename>
	<path>D:\666\YOLOV5\paper_data\VOC2024\images\Hispa\4056.jpg</path>
	<source>
		<database>Unknown</database>
	</source>
	<size>
		<width>3120</width>
		<height>3120</height>
		<depth>3</depth>
	</size>
	<segmented>0</segmented>
	<object>
		<name>Hispa</name>
		<pose>Unspecified</pose>
		<truncated>0</truncated>
		<difficult>0</difficult>
		<bndbox>
			<xmin>1943</xmin>
			<ymin>2226</ymin>
			<xmax>2000</xmax>
			<ymax>2296</ymax>
		</bndbox>
	</object>
	<object>
		<name>Hispa</name>
		<pose>Unspecified</pose>
		<truncated>0</truncated>
		<difficult>0</difficult>
		<bndbox>
			<xmin>1860</xmin>
			<ymin>2336</ymin>
			<xmax>1943</xmax>
			<ymax>2413</ymax>
		</bndbox>
	</object>
	<object>
		<name>Hispa</name>
		<pose>Unspecified</pose>
		<truncated>0</truncated>
		<difficult>0</difficult>
		<bndbox>
			<xmin>2085</xmin>
			<ymin>2496</ymin>
			<xmax>2133</xmax>
			<ymax>2541</ymax>
		</bndbox>
	</object>
	<object>
		<name>Hispa</name>
		<pose>Unspecified</pose>
		<truncated>0</truncated>
		<difficult>0</difficult>
		<bndbox>
			<xmin>2145</xmin>
			<ymin>2563</ymin>
			<xmax>2198</xmax>
			<ymax>2631</ymax>
		</bndbox>
	</object>
	<object>
		<name>Hispa</name>
		<pose>Unspecified</pose>
		<truncated>0</truncated>
		<difficult>0</difficult>
		<bndbox>
			<xmin>2535</xmin>
			<ymin>2758</ymin>
			<xmax>2580</xmax>
			<ymax>2796</ymax>
		</bndbox>
	</object>
	<object>
		<name>Hispa</name>
		<pose>Unspecified</pose>
		<truncated>0</truncated>
		<difficult>0</difficult>
		<bndbox>
			<xmin>2373</xmin>
			<ymin>2778</ymin>
			<xmax>2430</xmax>
			<ymax>2821</ymax>
		</bndbox>
	</object>
	<object>
		<name>Hispa</name>
		<pose>Unspecified</pose>
		<truncated>0</truncated>
		<difficult>0</difficult>
		<bndbox>
			<xmin>1440</xmin>
			<ymin>1738</ymin>
			<xmax>1490</xmax>
			<ymax>1776</ymax>
		</bndbox>
	</object>
	<object>
		<name>Hispa</name>
		<pose>Unspecified</pose>
		<truncated>0</truncated>
		<difficult>0</difficult>
		<bndbox>
			<xmin>1530</xmin>
			<ymin>2023</ymin>
			<xmax>1598</xmax>
			<ymax>2086</ymax>
		</bndbox>
	</object>
</annotation>
