<annotation>
	<folder>Hispa</folder>
	<filename>4253.jpg</filename>
	<path>D:\666\YOLOV5\paper_data\VOC2024\images\Hispa\4253.jpg</path>
	<source>
		<database>Unknown</database>
	</source>
	<size>
		<width>1459</width>
		<height>1459</height>
		<depth>3</depth>
	</size>
	<segmented>0</segmented>
	<object>
		<name>Hispa</name>
		<pose>Unspecified</pose>
		<truncated>0</truncated>
		<difficult>0</difficult>
		<bndbox>
			<xmin>1139</xmin>
			<ymin>169</ymin>
			<xmax>1179</xmax>
			<ymax>197</ymax>
		</bndbox>
	</object>
	<object>
		<name>Hispa</name>
		<pose>Unspecified</pose>
		<truncated>0</truncated>
		<difficult>0</difficult>
		<bndbox>
			<xmin>991</xmin>
			<ymin>338</ymin>
			<xmax>1078</xmax>
			<ymax>386</ymax>
		</bndbox>
	</object>
</annotation>
