<annotation>
	<folder>LeafBlast</folder>
	<filename>4477.jpg</filename>
	<path>D:\666\YOLOV5\paper_data\VOC2024\images\LeafBlast\4477.jpg</path>
	<source>
		<database>Unknown</database>
	</source>
	<size>
		<width>1741</width>
		<height>1741</height>
		<depth>3</depth>
	</size>
	<segmented>0</segmented>
	<object>
		<name>LeafBlast</name>
		<pose>Unspecified</pose>
		<truncated>0</truncated>
		<difficult>0</difficult>
		<bndbox>
			<xmin>823</xmin>
			<ymin>1102</ymin>
			<xmax>852</xmax>
			<ymax>1135</ymax>
		</bndbox>
	</object>
	<object>
		<name>LeafBlast</name>
		<pose>Unspecified</pose>
		<truncated>0</truncated>
		<difficult>0</difficult>
		<bndbox>
			<xmin>841</xmin>
			<ymin>884</ymin>
			<xmax>925</xmax>
			<ymax>957</ymax>
		</bndbox>
	</object>
</annotation>
