<annotation>
	<folder>LeafBlast</folder>
	<filename>4735.jpg</filename>
	<path>D:\666\YOLOV5\paper_data\VOC2024\images\LeafBlast\4735.jpg</path>
	<source>
		<database>Unknown</database>
	</source>
	<size>
		<width>1884</width>
		<height>1884</height>
		<depth>3</depth>
	</size>
	<segmented>0</segmented>
	<object>
		<name>LeafBlast</name>
		<pose>Unspecified</pose>
		<truncated>0</truncated>
		<difficult>0</difficult>
		<bndbox>
			<xmin>841</xmin>
			<ymin>898</ymin>
			<xmax>1059</xmax>
			<ymax>951</ymax>
		</bndbox>
	</object>
</annotation>
