<annotation>
	<folder>BacterialBlight</folder>
	<filename>571.jpg</filename>
	<path>D:\666\YOLOV5\paper_data\VOC2024\images\BacterialBlight\571.jpg</path>
	<source>
		<database>Unknown</database>
	</source>
	<size>
		<width>300</width>
		<height>300</height>
		<depth>3</depth>
	</size>
	<segmented>0</segmented>
	<object>
		<name>BacterialBlight</name>
		<pose>Unspecified</pose>
		<truncated>0</truncated>
		<difficult>0</difficult>
		<bndbox>
			<xmin>176</xmin>
			<ymin>217</ymin>
			<xmax>194</xmax>
			<ymax>229</ymax>
		</bndbox>
	</object>
	<object>
		<name>BacterialBlight</name>
		<pose>Unspecified</pose>
		<truncated>0</truncated>
		<difficult>0</difficult>
		<bndbox>
			<xmin>162</xmin>
			<ymin>204</ymin>
			<xmax>176</xmax>
			<ymax>216</ymax>
		</bndbox>
	</object>
	<object>
		<name>BacterialBlight</name>
		<pose>Unspecified</pose>
		<truncated>0</truncated>
		<difficult>0</difficult>
		<bndbox>
			<xmin>190</xmin>
			<ymin>130</ymin>
			<xmax>245</xmax>
			<ymax>200</ymax>
		</bndbox>
	</object>
	<object>
		<name>BacterialBlight</name>
		<pose>Unspecified</pose>
		<truncated>0</truncated>
		<difficult>0</difficult>
		<bndbox>
			<xmin>236</xmin>
			<ymin>93</ymin>
			<xmax>250</xmax>
			<ymax>127</ymax>
		</bndbox>
	</object>
	<object>
		<name>BacterialBlight</name>
		<pose>Unspecified</pose>
		<truncated>0</truncated>
		<difficult>0</difficult>
		<bndbox>
			<xmin>211</xmin>
			<ymin>47</ymin>
			<xmax>241</xmax>
			<ymax>87</ymax>
		</bndbox>
	</object>
	<object>
		<name>BacterialBlight</name>
		<pose>Unspecified</pose>
		<truncated>0</truncated>
		<difficult>0</difficult>
		<bndbox>
			<xmin>218</xmin>
			<ymin>11</ymin>
			<xmax>233</xmax>
			<ymax>38</ymax>
		</bndbox>
	</object>
</annotation>
